robocorp/vault/__init__.py
robocorp/vault/_adapters.py
robocorp/vault/_errors.py
robocorp/vault/_requests.py
robocorp/vault/_secrets.py
robocorp/vault/_utils.py
robocorp/vault/_vault.py
robocorp/vault/py.typed
robocorp_vault-1.3.8.dist-info/METADATA
robocorp_vault-1.3.8.dist-info/WHEEL
robocorp_vault-1.3.8.dist-info/RECORD
